<?xml version='1.0' encoding='UTF-8' standalone='yes' ?><hierarchy rotation="0"><node index="0" text="" resource-id="" class="android.widget.FrameLayout" package="com.bolao.android" content-desc="" checkable="false" checked="false" clickable="false" enabled="true" focusable="false" focused="false" scrollable="false" long-clickable="false" password="false" selected="false" bounds="[0,0][1080,2400]"><node index="0" text="" resource-id="" class="android.widget.LinearLayout" package="com.bolao.android" content-desc="" checkable="false" checked="false" clickable="false" enabled="true" focusable="false" focused="false" scrollable="false" long-clickable="false" password="false" selected="false" bounds="[0,0][1080,2400]"><node index="0" text="" resource-id="android:id/content" class="android.widget.FrameLayout" package="com.bolao.android" content-desc="" checkable="false" checked="false" clickable="false" enabled="true" focusable="false" focused="false" scrollable="false" long-clickable="false" password="false" selected="false" bounds="[0,0][1080,2400]"><node index="0" text="" resource-id="" class="androidx.compose.ui.platform.ComposeView" package="com.bolao.android" content-desc="" checkable="false" checked="false" clickable="false" enabled="true" focusable="false" focused="false" scrollable="false" long-clickable="false" password="false" selected="false" bounds="[0,0][1080,2400]"><node index="0" text="" resource-id="" class="android.view.View" package="com.bolao.android" content-desc="" checkable="false" checked="false" clickable="false" enabled="true" focusable="false" focused="false" scrollable="false" long-clickable="false" password="false" selected="false" bounds="[0,0][1080,2400]"><node index="0" text="" resource-id="" class="android.view.View" package="com.bolao.android" content-desc="" checkable="false" checked="false" clickable="false" enabled="true" focusable="false" focused="false" scrollable="false" long-clickable="false" password="false" selected="false" bounds="[0,0][1080,2400]"><node index="0" text="" resource-id="" class="android.view.View" package="com.bolao.android" content-desc="" checkable="false" checked="false" clickable="false" enabled="true" focusable="false" focused="false" scrollable="true" long-clickable="false" password="false" selected="false" bounds="[0,470][1080,2140]"><node index="0" text="" resource-id="" class="android.view.View" package="com.bolao.android" content-desc="" checkable="false" checked="false" clickable="false" enabled="true" focusable="false" focused="false" scrollable="false" long-clickable="false" password="false" selected="false" bounds="[40,510][1040,1237]"><node index="0" text="World Cup" resource-id="" class="android.widget.TextView" package="com.bolao.android" content-desc="" checkable="false" checked="false" clickable="false" enabled="true" focusable="false" focused="false" scrollable="false" long-clickable="false" password="false" selected="false" bounds="[80,540][248,577]" /><node index="1" text="Group A · Qui, 11/06 · 16:00" resource-id="" class="android.widget.TextView" package="com.bolao.android" content-desc="" checkable="false" checked="false" clickable="false" enabled="true" focusable="false" focused="false" scrollable="false" long-clickable="false" password="false" selected="false" bounds="[80,577][449,614]" /><node index="2" text="MEX" resource-id="" class="android.widget.TextView" package="com.bolao.android" content-desc="" checkable="false" checked="false" clickable="false" enabled="true" focusable="false" focused="false" scrollable="false" long-clickable="false" password="false" selected="false" bounds="[251,756][322,793]" /><node index="3" text="Mexico" resource-id="" class="android.widget.TextView" package="com.bolao.android" content-desc="" checkable="false" checked="false" clickable="false" enabled="true" focusable="false" focused="false" scrollable="false" long-clickable="false" password="false" selected="false" bounds="[226,864][346,907]" /><node index="4" text="" resource-id="" class="android.view.View" package="com.bolao.android" content-desc="" checkable="false" checked="false" clickable="true" enabled="false" focusable="false" focused="false" scrollable="false" long-clickable="false" password="false" selected="false" bounds="[126,912][246,1032]"><node index="0" text="" resource-id="" class="android.view.View" package="com.bolao.android" content-desc="Diminuir gols" checkable="false" checked="false" clickable="false" enabled="true" focusable="false" focused="false" scrollable="false" long-clickable="false" password="false" selected="false" bounds="[164,950][209,995]" /><node index="1" text="" resource-id="" class="android.widget.Button" package="com.bolao.android" content-desc="" checkable="false" checked="false" clickable="false" enabled="true" focusable="false" focused="false" scrollable="false" long-clickable="false" password="false" selected="false" bounds="[141,927][231,1017]" /></node><node index="5" text="0" resource-id="" class="android.widget.TextView" package="com.bolao.android" content-desc="" checkable="false" checked="false" clickable="false" enabled="true" focusable="false" focused="false" scrollable="false" long-clickable="false" password="false" selected="false" bounds="[231,929][326,1015]" /><node index="6" text="" resource-id="" class="android.view.View" package="com.bolao.android" content-desc="" checkable="false" checked="false" clickable="true" enabled="true" focusable="true" focused="false" scrollable="false" long-clickable="false" password="false" selected="false" bounds="[326,912][446,1032]"><node index="0" text="" resource-id="" class="android.view.View" package="com.bolao.android" content-desc="Aumentar gols" checkable="false" checked="false" clickable="false" enabled="true" focusable="false" focused="false" scrollable="false" long-clickable="false" password="false" selected="false" bounds="[364,950][409,995]" /><node index="1" text="" resource-id="" class="android.widget.Button" package="com.bolao.android" content-desc="" checkable="false" checked="false" clickable="false" enabled="true" focusable="false" focused="false" scrollable="false" long-clickable="false" password="false" selected="false" bounds="[341,927][431,1017]" /></node><node index="7" text="×" resource-id="" class="android.widget.TextView" package="com.bolao.android" content-desc="" checkable="false" checked="false" clickable="false" enabled="true" focusable="false" focused="false" scrollable="false" long-clickable="false" password="false" selected="false" bounds="[522,824][558,897]" /><node index="8" text="SOU" resource-id="" class="android.widget.TextView" package="com.bolao.android" content-desc="" checkable="false" checked="false" clickable="false" enabled="true" focusable="false" focused="false" scrollable="false" long-clickable="false" password="false" selected="false" bounds="[760,756][828,793]" /><node index="9" text="South Africa" resource-id="" class="android.widget.TextView" package="com.bolao.android" content-desc="" checkable="false" checked="false" clickable="false" enabled="true" focusable="false" focused="false" scrollable="false" long-clickable="false" password="false" selected="false" bounds="[687,864][902,907]" /><node index="10" text="" resource-id="" class="android.view.View" package="com.bolao.android" content-desc="" checkable="false" checked="false" clickable="true" enabled="false" focusable="false" focused="false" scrollable="false" long-clickable="false" password="false" selected="false" bounds="[634,912][754,1032]"><node index="0" text="" resource-id="" class="android.view.View" package="com.bolao.android" content-desc="Diminuir gols" checkable="false" checked="false" clickable="false" enabled="true" focusable="false" focused="false" scrollable="false" long-clickable="false" password="false" selected="false" bounds="[672,950][717,995]" /><node index="1" text="" resource-id="" class="android.widget.Button" package="com.bolao.android" content-desc="" checkable="false" checked="false" clickable="false" enabled="true" focusable="false" focused="false" scrollable="false" long-clickable="false" password="false" selected="false" bounds="[649,927][739,1017]" /></node><node index="11" text="0" resource-id="" class="android.widget.TextView" package="com.bolao.android" content-desc="" checkable="false" checked="false" clickable="false" enabled="true" focusable="false" focused="false" scrollable="false" long-clickable="false" password="false" selected="false" bounds="[739,929][834,1015]" /><node index="12" text="" resource-id="" class="android.view.View" package="com.bolao.android" content-desc="" checkable="false" checked="false" clickable="true" enabled="true" focusable="true" focused="false" scrollable="false" long-clickable="false" password="false" selected="false" bounds="[834,912][954,1032]"><node index="0" text="" resource-id="" class="android.view.View" package="com.bolao.android" content-desc="Aumentar gols" checkable="false" checked="false" clickable="false" enabled="true" focusable="false" focused="false" scrollable="false" long-clickable="false" password="false" selected="false" bounds="[872,950][917,995]" /><node index="1" text="" resource-id="" class="android.widget.Button" package="com.bolao.android" content-desc="" checkable="false" checked="false" clickable="false" enabled="true" focusable="false" focused="false" scrollable="false" long-clickable="false" password="false" selected="false" bounds="[849,927][939,1017]" /></node><node index="13" text="" resource-id="" class="android.view.View" package="com.bolao.android" content-desc="" checkable="false" checked="false" clickable="true" enabled="false" focusable="false" focused="false" scrollable="false" long-clickable="false" password="false" selected="false" bounds="[80,1077][1000,1197]"><node index="0" text="Confirmar Palpite" resource-id="" class="android.widget.TextView" package="com.bolao.android" content-desc="" checkable="false" checked="false" clickable="false" enabled="true" focusable="false" focused="false" scrollable="false" long-clickable="false" password="false" selected="false" bounds="[417,1116][729,1159]" /><node index="1" text="" resource-id="" class="android.widget.Button" package="com.bolao.android" content-desc="" checkable="false" checked="false" clickable="false" enabled="true" focusable="false" focused="false" scrollable="false" long-clickable="false" password="false" selected="false" bounds="[80,1087][1000,1187]" /></node></node><node index="1" text="" resource-id="" class="android.view.View" package="com.bolao.android" content-desc="" checkable="false" checked="false" clickable="false" enabled="true" focusable="false" focused="false" scrollable="false" long-clickable="false" password="false" selected="false" bounds="[40,1277][1040,2004]"><node index="0" text="World Cup" resource-id="" class="android.widget.TextView" package="com.bolao.android" content-desc="" checkable="false" checked="false" clickable="false" enabled="true" focusable="false" focused="false" scrollable="false" long-clickable="false" password="false" selected="false" bounds="[80,1307][248,1344]" /><node index="1" text="Group A · Qui, 11/06 · 23:00" resource-id="" class="android.widget.TextView" package="com.bolao.android" content-desc="" checkable="false" checked="false" clickable="false" enabled="true" focusable="false" focused="false" scrollable="false" long-clickable="false" password="false" selected="false" bounds="[80,1344][457,1381]" /><node index="2" text="SO1" resource-id="" class="android.widget.TextView" package="com.bolao.android" content-desc="" checkable="false" checked="false" clickable="false" enabled="true" focusable="false" focused="false" scrollable="false" long-clickable="false" password="false" selected="false" bounds="[258,1523][315,1560]" /><node index="3" text="South Korea" resource-id="" class="android.widget.TextView" package="com.bolao.android" content-desc="" checkable="false" checked="false" clickable="false" enabled="true" focusable="false" focused="false" scrollable="false" long-clickable="false" password="false" selected="false" bounds="[180,1631][392,1674]" /><node index="4" text="" resource-id="" class="android.view.View" package="com.bolao.android" content-desc="" checkable="false" checked="false" clickable="true" enabled="false" focusable="false" focused="false" scrollable="false" long-clickable="false" password="false" selected="false" bounds="[126,1679][246,1799]"><node index="0" text="" resource-id="" class="android.view.View" package="com.bolao.android" content-desc="Diminuir gols" checkable="false" checked="false" clickable="false" enabled="true" focusable="false" focused="false" scrollable="false" long-clickable="false" password="false" selected="false" bounds="[164,1717][209,1762]" /><node index="1" text="" resource-id="" class="android.widget.Button" package="com.bolao.android" content-desc="" checkable="false" checked="false" clickable="false" enabled="true" focusable="false" focused="false" scrollable="false" long-clickable="false" password="false" selected="false" bounds="[141,1694][231,1784]" /></node><node index="5" text="0" resource-id="" class="android.widget.TextView" package="com.bolao.android" content-desc="" checkable="false" checked="false" clickable="false" enabled="true" focusable="false" focused="false" scrollable="false" long-clickable="false" password="false" selected="false" bounds="[231,1696][326,1782]" /><node index="6" text="" resource-id="" class="android.view.View" package="com.bolao.android" content-desc="" checkable="false" checked="false" clickable="true" enabled="true" focusable="true" focused="false" scrollable="false" long-clickable="false" password="false" selected="false" bounds="[326,1679][446,1799]"><node index="0" text="" resource-id="" class="android.view.View" package="com.bolao.android" content-desc="Aumentar gols" checkable="false" checked="false" clickable="false" enabled="true" focusable="false" focused="false" scrollable="false" long-clickable="false" password="false" selected="false" bounds="[364,1717][409,1762]" /><node index="1" text="" resource-id="" class="android.widget.Button" package="com.bolao.android" content-desc="" checkable="false" checked="false" clickable="false" enabled="true" focusable="false" focused="false" scrollable="false" long-clickable="false" password="false" selected="false" bounds="[341,1694][431,1784]" /></node><node index="7" text="×" resource-id="" class="android.widget.TextView" package="com.bolao.android" content-desc="" checkable="false" checked="false" clickable="false" enabled="true" focusable="false" focused="false" scrollable="false" long-clickable="false" password="false" selected="false" bounds="[522,1591][558,1664]" /><node index="8" text="CZE" resource-id="" class="android.widget.TextView" package="com.bolao.android" content-desc="" checkable="false" checked="false" clickable="false" enabled="true" focusable="false" focused="false" scrollable="false" long-clickable="false" password="false" selected="false" bounds="[763,1523][825,1560]" /><node index="9" text="Czechia" resource-id="" class="android.widget.TextView" package="com.bolao.android" content-desc="" checkable="false" checked="false" clickable="false" enabled="true" focusable="false" focused="false" scrollable="false" long-clickable="false" password="false" selected="false" bounds="[726,1631][862,1674]" /><node index="10" text="" resource-id="" class="android.view.View" package="com.bolao.android" content-desc="" checkable="false" checked="false" clickable="true" enabled="true" focusable="true" focused="false" scrollable="false" long-clickable="false" password="false" selected="false" bounds="[634,1679][754,1799]"><node index="0" text="" resource-id="" class="android.view.View" package="com.bolao.android" content-desc="Diminuir gols" checkable="false" checked="false" clickable="false" enabled="true" focusable="false" focused="false" scrollable="false" long-clickable="false" password="false" selected="false" bounds="[672,1717][717,1762]" /><node index="1" text="" resource-id="" class="android.widget.Button" package="com.bolao.android" content-desc="" checkable="false" checked="false" clickable="false" enabled="true" focusable="false" focused="false" scrollable="false" long-clickable="false" password="false" selected="false" bounds="[649,1694][739,1784]" /></node><node index="11" text="2" resource-id="" class="android.widget.TextView" package="com.bolao.android" content-desc="" checkable="false" checked="false" clickable="false" enabled="true" focusable="false" focused="false" scrollable="false" long-clickable="false" password="false" selected="false" bounds="[739,1696][834,1782]" /><node index="12" text="" resource-id="" class="android.view.View" package="com.bolao.android" content-desc="" checkable="false" checked="false" clickable="true" enabled="true" focusable="true" focused="false" scrollable="false" long-clickable="false" password="false" selected="false" bounds="[834,1679][954,1799]"><node index="0" text="" resource-id="" class="android.view.View" package="com.bolao.android" content-desc="Aumentar gols" checkable="false" checked="false" clickable="false" enabled="true" focusable="false" focused="false" scrollable="false" long-clickable="false" password="false" selected="false" bounds="[872,1717][917,1762]" /><node index="1" text="" resource-id="" class="android.widget.Button" package="com.bolao.android" content-desc="" checkable="false" checked="false" clickable="false" enabled="true" focusable="false" focused="false" scrollable="false" long-clickable="false" password="false" selected="false" bounds="[849,1694][939,1784]" /></node><node index="13" text="" resource-id="" class="android.view.View" package="com.bolao.android" content-desc="" checkable="false" checked="false" clickable="true" enabled="false" focusable="false" focused="false" scrollable="false" long-clickable="false" password="false" selected="false" bounds="[80,1844][1000,1964]"><node index="0" text="Atualizar Palpite" resource-id="" class="android.widget.TextView" package="com.bolao.android" content-desc="" checkable="false" checked="false" clickable="false" enabled="true" focusable="false" focused="false" scrollable="false" long-clickable="false" password="false" selected="false" bounds="[426,1883][719,1926]" /><node index="1" text="" resource-id="" class="android.widget.Button" package="com.bolao.android" content-desc="" checkable="false" checked="false" clickable="false" enabled="true" focusable="false" focused="false" scrollable="false" long-clickable="false" password="false" selected="false" bounds="[80,1854][1000,1954]" /></node></node><node index="2" text="" resource-id="" class="android.view.View" package="com.bolao.android" content-desc="" checkable="false" checked="false" clickable="false" enabled="true" focusable="false" focused="false" scrollable="false" long-clickable="false" password="false" selected="false" bounds="[40,2044][1040,2140]"><node index="0" text="World Cup" resource-id="" class="android.widget.TextView" package="com.bolao.android" content-desc="" checkable="false" checked="false" clickable="false" enabled="true" focusable="false" focused="false" scrollable="false" long-clickable="false" password="false" selected="false" bounds="[80,2074][248,2111]" /><node index="1" text="Group B · Sex, 12/06 · 16:00" resource-id="" class="android.widget.TextView" package="com.bolao.android" content-desc="" checkable="false" checked="false" clickable="false" enabled="true" focusable="false" focused="false" scrollable="false" long-clickable="false" password="false" selected="false" bounds="[80,2111][456,2140]" /></node></node><node index="1" text="" resource-id="" class="android.view.View" package="com.bolao.android" content-desc="" checkable="false" checked="false" clickable="false" enabled="true" focusable="false" focused="false" scrollable="false" long-clickable="false" password="false" selected="false" bounds="[0,0][1080,470]"><node index="0" text="" resource-id="" class="android.view.View" package="com.bolao.android" content-desc="" checkable="false" checked="false" clickable="false" enabled="true" focusable="false" focused="false" scrollable="false" long-clickable="false" password="false" selected="false" bounds="[40,127][317,213]" /><node index="1" text="" resource-id="" class="android.view.View" package="com.bolao.android" content-desc="" checkable="false" checked="false" clickable="true" enabled="true" focusable="true" focused="false" scrollable="false" long-clickable="false" password="false" selected="false" bounds="[950,110][1070,230]"><node index="0" text="" resource-id="" class="android.view.View" package="com.bolao.android" content-desc="Sair" checkable="false" checked="false" clickable="false" enabled="true" focusable="false" focused="false" scrollable="false" long-clickable="false" password="false" selected="false" bounds="[980,140][1040,200]" /><node index="1" text="" resource-id="" class="android.widget.Button" package="com.bolao.android" content-desc="" checkable="false" checked="false" clickable="false" enabled="true" focusable="false" focused="false" scrollable="false" long-clickable="false" password="false" selected="false" bounds="[960,120][1060,220]" /></node><node index="2" text="Palpites" resource-id="" class="android.widget.TextView" package="com.bolao.android" content-desc="" checkable="false" checked="false" clickable="false" enabled="true" focusable="false" focused="false" scrollable="false" long-clickable="false" password="false" selected="false" bounds="[40,332][317,418]" /></node><node index="2" text="" resource-id="" class="android.view.View" package="com.bolao.android" content-desc="" checkable="false" checked="false" clickable="false" enabled="true" focusable="false" focused="false" scrollable="false" long-clickable="false" password="false" selected="false" bounds="[0,2140][1080,2400]"><node index="0" text="" resource-id="" class="android.view.View" package="com.bolao.android" content-desc="" checkable="false" checked="false" clickable="false" enabled="true" focusable="false" focused="false" scrollable="false" long-clickable="false" password="false" selected="false" bounds="[0,2140][1080,2340]"><node index="0" text="" resource-id="" class="android.view.View" package="com.bolao.android" content-desc="" checkable="false" checked="false" clickable="false" enabled="true" focusable="true" focused="false" scrollable="false" long-clickable="false" password="false" selected="true" bounds="[0,2140][530,2340]"><node index="0" text="Palpites" resource-id="" class="android.widget.TextView" package="com.bolao.android" content-desc="" checkable="false" checked="false" clickable="false" enabled="true" focusable="false" focused="false" scrollable="false" long-clickable="false" password="false" selected="false" bounds="[201,2260][328,2300]" /><node index="1" text="" resource-id="" class="android.view.View" package="com.bolao.android" content-desc="" checkable="false" checked="false" clickable="false" enabled="true" focusable="false" focused="false" scrollable="false" long-clickable="false" password="false" selected="false" bounds="[235,2180][295,2240]" /><node index="2" text="" resource-id="" class="android.view.View" package="com.bolao.android" content-desc="" checkable="false" checked="false" clickable="false" enabled="true" focusable="false" focused="false" scrollable="false" long-clickable="false" password="false" selected="false" bounds="[0,2140][530,2340]" /></node><node index="1" text="" resource-id="" class="android.view.View" package="com.bolao.android" content-desc="" checkable="false" checked="false" clickable="true" enabled="true" focusable="true" focused="false" scrollable="false" long-clickable="false" password="false" selected="false" bounds="[550,2140][1080,2340]"><node index="0" text="Ligas" resource-id="" class="android.widget.TextView" package="com.bolao.android" content-desc="" checkable="false" checked="false" clickable="false" enabled="true" focusable="false" focused="false" scrollable="false" long-clickable="false" password="false" selected="false" bounds="[772,2260][857,2300]" /><node index="1" text="" resource-id="" class="android.view.View" package="com.bolao.android" content-desc="" checkable="false" checked="false" clickable="false" enabled="true" focusable="false" focused="false" scrollable="false" long-clickable="false" password="false" selected="false" bounds="[785,2180][845,2240]" /><node index="2" text="" resource-id="" class="android.view.View" package="com.bolao.android" content-desc="" checkable="false" checked="false" clickable="false" enabled="true" focusable="false" focused="false" scrollable="false" long-clickable="false" password="false" selected="false" bounds="[550,2140][1080,2340]" /></node></node></node></node></node></node></node></node></node></hierarchy>